Workbook
Name Aporte: OnePage!$D$9
Name dividendos: OnePage!$D$13
Name Patrimonio: OnePage!$D$12
Name qtd_anos: OnePage!$D$10
Name Rendimento_Carteira: OnePage!$D$5
Name Salrio: OnePage!$D$4
Name Sugestao_Investimento: OnePage!$D$6
Name taxa_mensal: OnePage!$D$11

Sheet OnePage
A1: Kadar Invest
B3: Configurações
B4: Salario | D4: 4200
B5: Rendimento Carteira | D5: 0.006
B6: Sugestão Investimento (30%) | D6: =Salrio*30% -> 1260
B8: Investimento Mensal
B9: Quanto investir por mês? | D9: 200
B10: Por quantos anos? | D10: 6
B11: Taxa de rendimento mensal? | D11: 0.01079
B12: Patrimônio acumulado? | D12: =FV(taxa_mensal,qtd_anos*12,Aporte*-1) -> 21606.04
B13: Dividendos mensais? | D13: =Patrimonio*Rendimento_Carteira -> 129.63624
B15: Cenários | D15: Dividendo
A16: 2 | B16: Quanto em 2 anos? | C16: =FV($D$11,$A16*12,$D$9*-1) -> 5445.5255 | D16: =C16*Rendimento_Carteira -> 32.673153
A17: 5 | B17: Quanto em 5 anos? | C17: =FV($D$11,$A17*12,$D$9*-1) -> 16755.383 | D17: =C17*Rendimento_Carteira -> 100.5323
A18: 10 | B18: Quanto em 10 anos? | C18: =FV($D$11,$A18*12,$D$9*-1) -> 48656.843 | D18: =C18*Rendimento_Carteira -> 291.94106
A19: 20 | B19: Quanto em 20 anos? | C19: =FV($D$11,$A19*12,$D$9*-1) -> 225039.68 | D19: =C19*$D$5 -> 1350.2381
A20: 30 | B20: Quanto em 30 anos? | C20: =FV($D$11,$A20*12,$D$9*-1) -> 864433.93 | D20: =C20*$D$5 -> 5186.6036
B22: Perfil | C22: Moderado
B23: Valor a ser investido por mês | C23: =Aporte -> 200
B25: Tipo de FII | C25: % Sugerido | D25: Valores
B26: Papel | C26: =VLOOKUP($C$22&"-"&B26,TabelaApoio!$A$2:$D$20,4,FALSE) -> 0.32 | D26: =$C$23*C26 -> 64
B27: Tijolo | C27: =VLOOKUP($C$22&"-"&B27,TabelaApoio!$A$2:$D$20,4,FALSE) -> 0.35 | D27: =$C$23*C27 -> 70
B28: Hibridos | C28: =VLOOKUP($C$22&"-"&B28,TabelaApoio!$A$2:$D$20,4,FALSE) -> 0.08 | D28: =$C$23*C28 -> 16
B29: FOF´s | C29: =VLOOKUP($C$22&"-"&B29,TabelaApoio!$A$2:$D$20,4,FALSE) -> 0.05 | D29: =$C$23*C29 -> 10
B30: Desenvolvimento | C30: =VLOOKUP($C$22&"-"&B30,TabelaApoio!$A$2:$D$20,4,FALSE) -> 0.1 | D30: =$C$23*C30 -> 20
B31: Hotelarias | C31: =VLOOKUP($C$22&"-"&B31,TabelaApoio!$A$2:$D$20,4,FALSE) -> 0.1 | D31: =$C$23*C31 -> 20
D32: =SUM(D26:D31) -> 200

Sheet TabelaApoio
A2: Chave | B2: Perfil | C2: Tipo de FII | D2: %
A3: =B3&"-"&C3 -> Conservador-Papel | B3: Conservador | C3: Papel | D3: 0.3
A4: =B4&"-"&C4 -> Conservador-Tijolo | B4: Conservador | C4: Tijolo | D4: 0.5
A5: =B5&"-"&C5 -> Conservador-Hibridos | B5: Conservador | C5: Hibridos | D5: 0.1
A6: =B6&"-"&C6 -> Conservador-FOF´s | B6: Conservador | C6: FOF´s | D6: 0.1 | J6: %
A7: =B7&"-"&C7 -> Conservador-Desenvolvimento | B7: Conservador | C7: Desenvolvimento | D7: 0 | I7: Moderado-Tijolo | J7: =VLOOKUP(I7,$A$2:$D$20,4,FALSE) -> 0.35
A8: =B8&"-"&C8 -> Conservador-Hotelarias | B8: Conservador | C8: Hotelarias | D8: 0
A9: =B9&"-"&C9 -> Moderado-Papel | B9: Moderado | C9: Papel | D9: 0.32
A10: =B10&"-"&C10 -> Moderado-Tijolo | B10: Moderado | C10: Tijolo | D10: 0.35
A11: =B11&"-"&C11 -> Moderado-Hibridos | B11: Moderado | C11: Hibridos | D11: 0.08
A12: =B12&"-"&C12 -> Moderado-FOF´s | B12: Moderado | C12: FOF´s | D12: 0.05
A13: =B13&"-"&C13 -> Moderado-Desenvolvimento | B13: Moderado | C13: Desenvolvimento | D13: 0.1
A14: =B14&"-"&C14 -> Moderado-Hotelarias | B14: Moderado | C14: Hotelarias | D14: 0.1
A15: =B15&"-"&C15 -> Agressivo-Papel | B15: Agressivo | C15: Papel | D15: 0.5
A16: =B16&"-"&C16 -> Agressivo-Tijolo | B16: Agressivo | C16: Tijolo | D16: 0.1
A17: =B17&"-"&C17 -> Agressivo-Hibridos | B17: Agressivo | C17: Hibridos | D17: 0.05
A18: =B18&"-"&C18 -> Agressivo-FOF´s | B18: Agressivo | C18: FOF´s | D18: 0.05
A19: =B19&"-"&C19 -> Agressivo-Desenvolvimento | B19: Agressivo | C19: Desenvolvimento | D19: 0.2
A20: =B20&"-"&C20 -> Agressivo-Hotelarias | B20: Agressivo | C20: Hotelarias | D20: 0.1
